svgdigitizer/__init__.py
svgdigitizer/entrypoint.py
svgdigitizer/exceptions.py
svgdigitizer/pdf.py
svgdigitizer/svg.py
svgdigitizer/svgfigure.py
svgdigitizer/svgplot.py
svgdigitizer/electrochemistry/__init__.py
svgdigitizer/electrochemistry/cv.py
svgdigitizer/test/__init__.py
svgdigitizer/test/cli.py
svgdigitizer-0.13.1.dist-info/licenses/LICENSE
svgdigitizer-0.13.1.dist-info/METADATA
svgdigitizer-0.13.1.dist-info/WHEEL
svgdigitizer-0.13.1.dist-info/entry_points.txt
svgdigitizer-0.13.1.dist-info/top_level.txt
svgdigitizer-0.13.1.dist-info/RECORD
