Metadata-Version: 2.4
Name: svgdigitizer
Version: 0.13.1
Summary: svgdigitizer is a Python library and command line tool to recover the measured data underlying plots in scientific publications.
Classifier: License :: OSI Approved :: GNU General Public License v3 or later (GPLv3+)
Requires-Python: >=3.10
License-File: LICENSE
Requires-Dist: astropy<8,>=5
Requires-Dist: click<9,>=8
Requires-Dist: frictionless<6,>=5.8.3
Requires-Dist: matplotlib<4,>=3.5
Requires-Dist: mergedeep<2,>=1.3.4
Requires-Dist: pandas<4,>=1.3
Requires-Dist: pillow<13,>=9
Requires-Dist: pybtex<0.26,>=0.25
Requires-Dist: pymupdf<1.26.6,>=1.26
Requires-Dist: pyyaml<7,>=6
Requires-Dist: requests<3,>2
Requires-Dist: scipy<2,>=1.7
Requires-Dist: svg.path<8,>=4.1
Requires-Dist: svgpathtools<2,>=1.4
Requires-Dist: svgwrite<2,>=1.4
Dynamic: license-file
